wythoff_construct/__init__.py
wythoff_construct/config.py
wythoff_construct/coxeter.py
wythoff_construct/groupGen.py
wythoff_construct/helpers.py
wythoff_construct/ui.py
wythoff_construct/uiElements.py
"wythoff_construct/savedKalidoscopes/[2,5]/faces.pkl"
"wythoff_construct/savedKalidoscopes/[2,5]/group.npy"
"wythoff_construct/savedKalidoscopes/[2,5]/intersections.npy"
"wythoff_construct/savedKalidoscopes/[3,4]/faces.pkl"
"wythoff_construct/savedKalidoscopes/[3,4]/group.npy"
"wythoff_construct/savedKalidoscopes/[3,4]/intersections.npy"
"wythoff_construct/savedKalidoscopes/[3,5]/faces.pkl"
"wythoff_construct/savedKalidoscopes/[3,5]/group.npy"
"wythoff_construct/savedKalidoscopes/[3,5]/intersections.npy"
"wythoff_construct/savedKalidoscopes/[3²,4]/faces.pkl"
"wythoff_construct/savedKalidoscopes/[3²,4]/group.npy"
"wythoff_construct/savedKalidoscopes/[3²,4]/intersections.npy"
"wythoff_construct/savedKalidoscopes/[3²,5]/faces.pkl"
"wythoff_construct/savedKalidoscopes/[3²,5]/group.npy"
"wythoff_construct/savedKalidoscopes/[3²,5]/intersections.npy"
wythoff_construct/savedKalidoscopes/[3²]/faces.pkl
wythoff_construct/savedKalidoscopes/[3²]/group.npy
wythoff_construct/savedKalidoscopes/[3²]/intersections.npy
"wythoff_construct/savedKalidoscopes/[3³,4]/faces.pkl"
"wythoff_construct/savedKalidoscopes/[3³,4]/group.npy"
"wythoff_construct/savedKalidoscopes/[3³,4]/intersections.npy"
wythoff_construct/savedKalidoscopes/[3³]/faces.pkl
wythoff_construct/savedKalidoscopes/[3³]/group.npy
wythoff_construct/savedKalidoscopes/[3³]/intersections.npy
wythoff_construct/savedKalidoscopes/[3⁴]/faces.pkl
wythoff_construct/savedKalidoscopes/[3⁴]/group.npy
wythoff_construct/savedKalidoscopes/[3⁴]/intersections.npy
wythoff_construct-0.2.5.data/scripts/wythoff-construct
wythoff_construct-0.2.5.dist-info/LICENCE
wythoff_construct-0.2.5.dist-info/METADATA
wythoff_construct-0.2.5.dist-info/WHEEL
wythoff_construct-0.2.5.dist-info/entry_points.txt
wythoff_construct-0.2.5.dist-info/top_level.txt
wythoff_construct-0.2.5.dist-info/RECORD
