Metadata-Version: 2.1
Name: wythoff-construct
Version: 0.2.5
Summary: Constructs and visualizes hyperdimensional polytopes created using Wythoff construction
Home-page: https://github.com/PrinceOfPuppers/wythoff-construct
Author: Joshua McPherson
Author-email: joshuamcpherson5@gmail.com
Classifier: Programming Language :: Python :: 3.6
Classifier: Programming Language :: Python :: 3.7
Classifier: Programming Language :: Python :: 3.8
Classifier: Programming Language :: Python :: 3.9
Classifier: License :: OSI Approved :: MIT License
Classifier: Operating System :: OS Independent
Classifier: Environment :: X11 Applications :: Qt
Requires-Python: >=3.6
License-File: LICENCE
Requires-Dist: numpy
Requires-Dist: scipy
Requires-Dist: PyQt5
Requires-Dist: vtk
Requires-Dist: mayavi
